barseq/__init__.py
barseq/main.py
barseq/process_reads.py
barseq/utils.py
barseq/tests/__init__.py
barseq/tests/test_functions.py
barseq/tests/test_main.py
barseq/tests/test_setup.py
barseq-1.0.1.data/scripts/barseq
barseq-1.0.1.dist-info/LICENSE
barseq-1.0.1.dist-info/METADATA
barseq-1.0.1.dist-info/WHEEL
barseq-1.0.1.dist-info/top_level.txt
barseq-1.0.1.dist-info/RECORD
