Metadata-Version: 2.1
Name: barseq
Version: 1.0.1
Summary: Analysis of barseq data.
Home-page: https://github.com/mjmlab/barseq
Author: Emanuel Burgos
Author-email: eburgos@wisc.edu
License: BSD
Platform: UNKNOWN
Classifier: Development Status :: 5 - Production/Stable
Classifier: Environment :: MacOS X
Classifier: Intended Audience :: Science/Research
Classifier: License :: OSI Approved :: BSD License
Classifier: Programming Language :: Python :: 3
Classifier: Topic :: Scientific/Engineering :: Bio-Informatics
Requires-Dist: pandas (>=0.24.2)
Requires-Dist: screed (>=1.0)
Requires-Dist: pytest (>=4.6.2)
Requires-Dist: pytest-cov (>=2.7.1)
Requires-Dist: matplotlib (>=1.5.0)
Requires-Dist: seaborn (>=0.6.0)
Requires-Dist: numpy (>=1.10.0)
Requires-Dist: python-Levenshtein (>=0.12.0)
Requires-Dist: regex (>=2019.05.25)
